HITrack/HITrack.py
HITrack/__init__.py
HITrack/constants.py
HITrack/utils.py
HITrack/HumanVisualizer/HumanVisualizer.py
HITrack/HumanVisualizer/Visualizer.py
HITrack/HumanVisualizer/__init__.py
HITrack/KeypointTracker/KeypointTracker.py
HITrack/KeypointTracker/__init__.py
HITrack/KeypointTracker/reg_model_1.cbm
HITrack/Networks/__init__.py
HITrack/Networks/Detection/YOLOv7.py
HITrack/Networks/Detection/__init__.py
HITrack/Networks/Pose2D/VITPose.py
HITrack/Networks/Pose2D/__init__.py
HITrack/Networks/Pose2D/VitPose/__init__.py
HITrack/Networks/Pose2D/VitPose/model.py
HITrack/Networks/Pose2D/VitPose/backbone/__init__.py
HITrack/Networks/Pose2D/VitPose/backbone/vit.py
HITrack/Networks/Pose2D/VitPose/configs/ViTPose_base_coco_256x192.py
HITrack/Networks/Pose2D/VitPose/configs/ViTPose_huge_coco_256x192.py
HITrack/Networks/Pose2D/VitPose/configs/ViTPose_large_coco_256x192.py
HITrack/Networks/Pose2D/VitPose/configs/__init__.py
HITrack/Networks/Pose2D/VitPose/head/__init__.py
HITrack/Networks/Pose2D/VitPose/head/topdown_heatmap_base_head.py
HITrack/Networks/Pose2D/VitPose/head/topdown_heatmap_simple_head.py
HITrack/Networks/Pose2D/VitPose/utils/__init__.py
HITrack/Networks/Pose2D/VitPose/utils/top_down_eval.py
HITrack/Networks/Pose2D/VitPose/utils/util.py
HITrack/Networks/Pose2D/VitPose/utils/post_processing/__init__.py
HITrack/Networks/Pose2D/VitPose/utils/post_processing/post_transforms.py
HITrack/Networks/PoseTo3D/MHFORMER.py
HITrack/Networks/PoseTo3D/__init__.py
HITrack/Networks/PoseTo3D/MHFormer/__init__.py
HITrack/Networks/PoseTo3D/MHFormer/camera.py
HITrack/Networks/PoseTo3D/MHFormer/mhformer.py
HITrack/Networks/PoseTo3D/MHFormer/module/__init__.py
HITrack/Networks/PoseTo3D/MHFormer/module/trans.py
HITrack/Networks/PoseTo3D/MHFormer/module/trans_hypothesis.py
HITrack-1.0.4.dist-info/LICENSE
HITrack-1.0.4.dist-info/METADATA
HITrack-1.0.4.dist-info/WHEEL
HITrack-1.0.4.dist-info/top_level.txt
HITrack-1.0.4.dist-info/RECORD
