Metadata-Version: 2.1
Name: HITrack
Version: 1.0.4
Summary: 3D scene on a monocular video
Home-page: https://github.com/Kirill-Shokhin/HITrack
Author: Kirill Shokhin
Author-email: kashokhin@gmail.com
License: MIT
Keywords: HITrack
Classifier: Programming Language :: Python :: 3.7
Classifier: Programming Language :: Python :: 3.8
Classifier: Programming Language :: Python :: 3.9
Classifier: Programming Language :: Python :: 3.10
Classifier: Programming Language :: Python :: 3.11
Classifier: License :: OSI Approved :: MIT License
Classifier: Operating System :: OS Independent
Requires-Python: >=3.7
License-File: LICENSE
Requires-Dist: numpy (>=1.23.5)
Requires-Dist: torch (>=1.13.1)
Requires-Dist: opencv-python (>=4.7.0.68)
Requires-Dist: torchvision (>=0.14.1)
Requires-Dist: timm (>=0.4.9)
Requires-Dist: einops (>=0.6.0)
Requires-Dist: tqdm (>=4.64.1)
Requires-Dist: requests (>=2.28.1)
Requires-Dist: pandas (>=1.4.4)
Requires-Dist: plotly (>=5.9.0)
Requires-Dist: matplotlib (>=3.5.2)
Requires-Dist: filterpy (>=1.4.5)
Requires-Dist: catboost (>=1.1.1)
Requires-Dist: yolov7detect (>=1.0.1)
Requires-Dist: scipy (>=1.9.1)
